{
  "$schema": "https://ui.shadcn.com/schema/registry.json",
  "name": "3D informatica",
  "homepage": "https://www.3di.it/",
  "items": [
    {
      "name": "hello-world",
      "type": "registry:ui",
      "title": "Hello World",
      "description": "A simple hello world component.",
      "files": [
        {
          "path": "registry/area/hello-world/hello-world.tsx",
          "type": "registry:ui"
        }
      ]
    },
    {
      "name": "navbar",
      "type": "registry:ui",
      "title": "Nav Bar",
      "description": "A simple nav bar component.",
      "files": [
        {
          "path": "registry/area/nav-bar/navbar.tsx",
          "type": "registry:ui"
        }
      ]
    }
  ]
}
